{
  "card_name": "트래블러스 체크카드",
  "card_type": "체크카드",
  "keyword": "할인",
  "target_user": "본인",
  "brand": "MASTER",
  "sections": [
    {
      "heading": "서비스 개요 및 주요 혜택",
      "subheading": "국내외 결제·출금·환급·수수료 면제, 여행에 특화된 혜택",
      "benefits": [
        "KB Pay 결제 시 건당 1만원 이상 200원 환급(월 10회, 최대 2천원)",
        "커피전문점 5천원 이상 결제 1천원 환급(월 1회), 제과/아이스크림 1만원 이상 결제 2천원 환급(월 1회)",
        "철도 2만원 이상 5,000원(월 1회), 고속버스 1만원 이상 2,000원(월 1회)",
        "주차장 1천원 이상 500원 환급(월 6회), 전국맛집(푸드인 선정) 2만원 이상 5,000원(월 1회)",
        "해외 가맹점/ATM/온라인 결제·출금 시 국제브랜드수수료 1%, 해외서비스수수료 0.25% 월 10회(ATM은 3회)까지 면제"
      ]
    },
    {
      "heading": "이용/출금 구조 안내",
      "subheading": "국내·해외 온오프라인/ATM 이용 방법 및 설정",
      "etc": [
        "국내 가맹점/ATM은 국민은행 입출금통장에서 원화 출금",
        "해외 온/오프라인 결제·출금은 KB Pay 외화머니(현지통화) 또는 KB국민은행 외화통장(USD·지정 가능)에서 출금",
        "KB Pay 외화머니는 앱에서 충전·환전·계좌설정 가능, KB국민은행 외화통장도 연동 설정 필요",
        "해외 ATM·가맹점 이용 시 결제계좌에 외화 잔액 필수, DCC(해외원화결제서비스)는 불가",
        "해외ATM 출금 건당/월간 한도, 국내외 ATM 모두 이용 가능"
      ]
    },
    {
      "heading": "이용 조건 및 주요 제한",
      "subheading": "전월 실적, 제외대상, 업종·매장 조건",
      "condition": [
        "전월 20만원 이상 실적 시 혜택 제공(일부는 실적 무관, 최초 출금 등 명시사항 준수)",
        "할인/환급 제외: 상품권·선불카드(구매/충전), 후불교통요금, 무승인, 정부지원금, 포인트 충전, 대학등록금, 연체료, 지방세, 수수료, 취소(승인/매입/환급 관련) 등",
        "PG·간편결제, 백화점·대형마트·호텔·철도입점매장 등 업종제한, 업종가맹점코드 반드시 일치 필요",
        "환급 한도는 월별 리셋(이월 불가), 매출 취소시 한도 복원 지연 됨"
      ]
    },
    {
      "heading": "해외 이용/ATM·수수료 정책",
      "subheading": "최저수수료, 승인/출금 방식, 환율 및 DCC 차단",
      "etc": [
        "해외 온/오프라인 가맹점·ATM 이용 시 국제브랜드 수수료(1%) 및 KB해외서비스수수료(0.25%) 합산, 월 10회(ATM 건당 3회)까지 면제, 이후 부과",
        "KB국민은행 최초 고시 전신환매도율 기준 환산(미지원통화는 USD 환산)",
        "승인 시 해당 외화 결제계좌에서 즉시 출금(무승인/T&E 업종은 매입일 출금)",
        "DCC(해외원화결제서비스) 차단, 해외가맹점 결제는 반드시 외화 선택 권장",
        "KB Pay 앱·KB국민은행 홈페이지에서 결제계좌 변경·관리 가능, 국내 ATM 입출금 별도 운영"
      ]
    },
    {
      "heading": "기타 유의사항 및 법적 안내",
      "subheading": "발급·한도·연체·청소년 등 종합 주의사항",
      "condition": [
        "발급: 만 14세 이상 내국인만 가능",
        "계좌·카드 한도: 만14~18세 추가 제한(기본 KB국민카드 정책 준용), 1회 최대, 월 출금/사용액 개별 한도에 따름",
        "연회비 없음, 카드 남용 및 과다 발급·사용 시 신용등급 및 한도 하락 등 불이익 주의",
        "연체 시 회원별·상품별 정상이자율+3%p, 최고 연20% 적용, 일정기간 연체시 모든 원리금 변제의무 발생",
        "부가서비스·혜택 변경 시 사전고지, 카드사 정책변경·법령개정 시 별도 안내"
      ]
    }
  ]
}
