{
  "card_name": "그린재킷 체크카드",
  "card_type": "체크카드",
  "keyword": "문화/레져",
  "brand": "국내, VISA",
  "target_user": "본인",
  "benefits": [
    "골프연습장/스크린골프에서 전월 실적 조건 충족 시 5% 할인, 월 최대 10만 원",
    "골프관광(그린재킷투어)에서 5% 할인, 월 최대 10만 원, 전용 홈페이지나 앱 결제 시 적용",
    "골프웨어/골프용품에서 5% 할인, 월 최대 10만 원",
    "커피/디저트에서 전월 실적 조건 충족 시 10% 할인, 월 최대 1만 원",
    "영화에서 전월 실적 조건 충족 시 5% 할인, 월 최대 1만 원",
    "서점에서 전월 실적 조건 충족 시 5% 할인, 월 최대 1만 원"
  ],
  "benefit_conditions": [
    "전월 실적 30만 원 이상 시 혜택 적용",
    "골프관광은 전용 홈페이지나 앱 결제 시 적용",
    "백화점 등 입점 매장, 온라인 결제, 상품권 이용분은 할인 제외",
    "후불교통요금, 무승인금액, 정부지원금, 포인트리 충전금액, 대학 등록금, 상품권 및 선불카드 구입 금액, 연체료, 지방세, 취소금액, 각종 수수료 및 이자는 실적 산정에서 제외"
  ],
  "fee": "연회비 없음",
  "overseas_usage": "해외에서 사용 가능",
  "release_date": "2021.06.14"
}